core/__init__.py
core/randomizer.py
generators/__init__.py
generators/name_generator.py
neym-0.1.0.dist-info/METADATA
neym-0.1.0.dist-info/WHEEL
neym-0.1.0.dist-info/top_level.txt
neym-0.1.0.dist-info/RECORD
