Metadata-Version: 2.4
Name: neym
Version: 0.1.0
Summary: A simple name generator library
Author: Developed by Arif
License-Expression: MIT
Requires-Python: >=3.8
